{
  "backtest": {
    "run_id": 5,
    "run_at": "2026-06-23 07:30:00",
    "run_status": "partial",
    "total_results": 0,
    "avg_return": 0
  },
  "pending": [
    {
      "code": "002579",
      "name": "中京电子",
      "score": 92,
      "score_tracker": 30,
      "score_sector": 25,
      "score_quality": 15,
      "score_technical": 15,
      "score_sentiment": 7,
      "trigger_price": 20.32,
      "trigger_condition": "利润保护，守19.50持有，不开新仓",
      "signal_status": "pending",
      "latest_price": null,
      "change_pct": null,
      "volume_amount_yi": null
    },
    {
      "code": "000725",
      "name": "京东方A",
      "score": 74,
      "score_tracker": 20,
      "score_sector": 25,
      "score_quality": 12,
      "score_technical": 10,
      "score_sentiment": 7,
      "trigger_price": 6.55,
      "trigger_condition": "回踩6.30-6.54不破+放量重返",
      "signal_status": "pending",
      "latest_price": null,
      "change_pct": null,
      "volume_amount_yi": null
    },
    {
      "code": "002463",
      "name": "沪电股份",
      "score": 72,
      "score_tracker": 20,
      "score_sector": 25,
      "score_quality": 12,
      "score_technical": 8,
      "score_sentiment": 7,
      "trigger_price": 147.9,
      "trigger_condition": "回踩145.70不破+站回149.90",
      "signal_status": "pending",
      "latest_price": null,
      "change_pct": null,
      "volume_amount_yi": null
    },
    {
      "code": "600111",
      "name": "北方稀土",
      "score": 67,
      "score_tracker": 20,
      "score_sector": 20,
      "score_quality": 12,
      "score_technical": 8,
      "score_sentiment": 7,
      "trigger_price": 51.4,
      "trigger_condition": "回踩49.08-49.66不破",
      "signal_status": "pending",
      "latest_price": null,
      "change_pct": null,
      "volume_amount_yi": null
    }
  ],
  "summary": {
    "total_signals": 4,
    "high_score_count": 1
  }
}